LICENSE.txt
MANIFEST.in
requirements.txt
setup.cfg
setup.py
sphinx_molview_theme/__init__.py
sphinx_molview_theme.egg-info/PKG-INFO
sphinx_molview_theme.egg-info/SOURCES.txt
sphinx_molview_theme.egg-info/dependency_links.txt
sphinx_molview_theme.egg-info/requires.txt
sphinx_molview_theme.egg-info/top_level.txt
sphinx_molview_theme/molview/layout.html
sphinx_molview_theme/molview/navbar.html
sphinx_molview_theme/molview/relations.html
sphinx_molview_theme/molview/theme.conf
sphinx_molview_theme/molview/static/adjustments.css
sphinx_molview_theme/molview/static/favicon.ico