Metadata-Version: 1.0
Name: sphinx-molview-theme
Version: 0.0.1
Summary: Sphinx theme for MolView
Home-page: https://github.com/molview/sphinx-molview-theme
Author: Herman Bergwerf
Author-email: hermanbergwerf@gmail.com
License: MIT
Keywords: sphinx,molview,theme
Platform: UNKNOWN
